django_offline_messages-0.3.7.dist-info/DESCRIPTION.rst
django_offline_messages-0.3.7.dist-info/METADATA
django_offline_messages-0.3.7.dist-info/RECORD
django_offline_messages-0.3.7.dist-info/WHEEL
django_offline_messages-0.3.7.dist-info/metadata.json
django_offline_messages-0.3.7.dist-info/top_level.txt
offline_messages/__init__.py
offline_messages/admin.py
offline_messages/models.py
offline_messages/storage.py
offline_messages/utils.py
offline_messages/migrations/0001_initial.py
offline_messages/migrations/__init__.py
offline_messages/south_migrations/0001_initial.py
offline_messages/south_migrations/0002_auto__add_field_offlinemessage_level.py
offline_messages/south_migrations/0003_auto__add_field_offlinemessage_tags.py
offline_messages/south_migrations/0004_auto__del_field_offlinemessage_tags.py
offline_messages/south_migrations/0005_auto__add_field_offlinemessage_read__add_field_offlinemessage_content_.py
offline_messages/south_migrations/__init__.py
