Metadata-Version: 2.0
Name: django-offline-messages
Version: 0.3.7
Summary: A package that implements offline messages for Django plus more
Home-page: https://github.com/dym/django-offline-messages
Author: Dmitriy Budashny
Author-email: dmitriy.budashny@gmail.com
License: BSD
Keywords: django offline messages
Platform: UNKNOWN
Classifier: Development Status :: 3 - Alpha
Classifier: Environment :: Web Environment
Classifier: Framework :: Django
Classifier: Intended Audience :: Developers
Classifier: License :: OSI Approved :: BSD License
Classifier: Operating System :: OS Independent
Classifier: Programming Language :: Python
Classifier: Topic :: Software Development :: Libraries :: Python Modules
Requires-Dist: django-jsonfield
